npts/__init__.py
npts/core.py
npts-0.0.1.dist-info/METADATA
npts-0.0.1.dist-info/WHEEL
npts-0.0.1.dist-info/entry_points.txt
npts-0.0.1.dist-info/licenses/LICENSE
npts-0.0.1.dist-info/RECORD
