Metadata-Version: 2.1
Name: npts
Version: 0.0.1
Summary: neeky's perf tool
Project-URL: Homepage, https://github.com/pypa/sampleproject
Author-email: LeXing Jiang <1721900707@qq.com>, neeky <neeky@live.com>
License-File: LICENSE
Classifier: License :: OSI Approved :: MIT License
Classifier: Operating System :: OS Independent
Classifier: Programming Language :: Python :: 3
Requires-Python: >=3.8
Requires-Dist: django==4.1.2
